livesync/__init__.py
livesync/folder.py
livesync/livesync.py
livesync/mutex.py
livesync/run_subprocess.py
livesync/sync.py
LiveSync-0.3.4.dist-info/LICENSE
LiveSync-0.3.4.dist-info/METADATA
LiveSync-0.3.4.dist-info/WHEEL
LiveSync-0.3.4.dist-info/entry_points.txt
LiveSync-0.3.4.dist-info/top_level.txt
LiveSync-0.3.4.dist-info/RECORD
