Metadata-Version: 2.1
Name: LiveSync
Version: 0.3.4
Summary: Repeatedly synchronize local workspace with a (slow) remote machine
Home-page: https://github.com/zauberzeug/livesync
Author: Zauberzeug GmbH
Author-email: info@zauberzeug.com
License: MIT
Keywords: sync remote watch filesystem development deploy live hot reload
Requires-Python: >=3.7
License-File: LICENSE
Requires-Dist: pathspec
Requires-Dist: watchfiles
